{
  "transactions": [
    { "id": 1, "type": "Income", "category": "Income", "amount": 2500, "date": "2024-01-05", "description": "Monthly salary" },
    { "id": 2, "type": "Expense", "category": "Rent", "amount": 900, "date": "2024-01-06", "description": "Monthly rent" },
    { "id": 3, "type": "Expense", "category": "Groceries", "amount": 120.5, "date": "2024-01-10", "description": "Groceries" },
    { "id": 4, "type": "Expense", "category": "Utilities", "amount": 80, "date": "2024-01-15", "description": "Water and electric" },
    { "id": 5, "type": "Income", "category": "Second job", "amount": 400, "date": "2024-01-18", "description": "Evening shift" },
    { "id": 6, "type": "Expense", "category": "Fun", "amount": 60, "date": "2024-01-20", "description": "Concert ticket" },
    { "id": 7, "type": "Savings & Investment", "category": "Savings", "amount": 500, "date": "2024-01-25", "description": "Monthly saving" },
    { "id": 8, "type": "Income", "category": "other", "amount": 100, "date": "2024-02-01", "description": "Gift" },
    { "id": 9, "type": "Expense", "category": "Clothes", "amount": 150, "date": "2024-02-02", "description": "Winter jacket" },
    { "id": 10, "type": "Expense", "category": "Transportation", "amount": 50, "date": "2024-02-04", "description": "Train pass" },
    { "id": 11, "type": "Savings & Investment", "category": "Investment", "amount": 300, "date": "2024-02-06", "description": "ETF purchase" },
    { "id": 12, "type": "Expense", "category": "Health", "amount": 75, "date": "2024-02-07", "description": "Dentist visit" },
    { "id": 13, "type": "Income", "category": "Income", "amount": 2500, "date": "2024-02-10", "description": "February salary" },
    { "id": 14, "type": "Expense", "category": "Friends", "amount": 45, "date": "2024-02-12", "description": "Birthday dinner" },
    { "id": 15, "type": "Savings & Investment", "category": "Savings", "amount": 400, "date": "2024-02-14", "description": "Savings deposit" },
    { "id": 16, "type": "Income", "category": "Second job", "amount": 300, "date": "2024-02-15", "description": "Freelance task" },
    { "id": 17, "type": "Expense", "category": "Other", "amount": 90, "date": "2024-02-18", "description": "Misc purchase" },
    { "id": 18, "type": "Expense", "category": "Utilities", "amount": 70, "date": "2024-02-20", "description": "Gas bill" },
    { "id": 19, "type": "Savings & Investment", "category": "Investment", "amount": 250, "date": "2024-02-25", "description": "Stock buy" },
    { "id": 20, "type": "Income", "category": "Income", "amount": 2700, "date": "2024-03-01", "description": "March salary" },
    { "id": 21, "type": "Income", "category": "Second job", "amount": 350, "date": "2025-07-05", "description": "Freelance project" },
    { "id": 22, "type": "Expense", "category": "Transportation", "amount": 45, "date": "2025-07-07", "description": "Monthly metro pass" },
    { "id": 23, "type": "Savings & Investment", "category": "Savings", "amount": 400, "date": "2025-07-10", "description": "Savings deposit" },
    { "id": 24, "type": "Expense", "category": "Fun", "amount": 90, "date": "2025-07-12", "description": "Movie and dinner" },
    { "id": 25, "type": "Income", "category": "Income", "amount": 2600, "date": "2025-07-15", "description": "July salary" }
  ]
}
